wrighter/__init__.py
wrighter/async_wrighter.py
wrighter/constants.py
wrighter/core.py
wrighter/options.py
wrighter/plugin.py
wrighter/plugin_manager.py
wrighter/sync_wrighter.py
wrighter-0.1.2.dist-info/LICENSE
wrighter-0.1.2.dist-info/METADATA
wrighter-0.1.2.dist-info/WHEEL
wrighter-0.1.2.dist-info/top_level.txt
wrighter-0.1.2.dist-info/RECORD
