Metadata-Version: 2.1
Name: wrighter
Version: 0.1.2
Summary: eb scraping/browser automation framework built on Playwright
Author-email: Žiga Ivanšek <ziga.ivansek@gmail.com>
Project-URL: Repository, https://github.com/zigai/wrighter
Keywords: wrighter,plugins,wrighter plugins,playwright plugins,web scraping,web automation,browser automation plugins
Classifier: Programming Language :: Python
Classifier: Programming Language :: Python :: 3.10
Classifier: Programming Language :: Python :: 3 :: Only
Classifier: Topic :: Software Development :: Libraries :: Python Modules
Classifier: Topic :: Software Development :: Testing
Classifier: Topic :: Internet :: WWW/HTTP :: Browsers
Classifier: Intended Audience :: Developers
Classifier: License :: OSI Approved
Classifier: License :: OSI Approved :: MIT License
Classifier: Operating System :: OS Independent
Requires-Python: >=3.10
License-File: LICENSE
Requires-Dist: playwright (>=1.33.0)
Requires-Dist: pydantic (>=1.10.8)
Requires-Dist: playwright-stealth (>=1.0.5)
Requires-Dist: stdl (>=0.4.4)
Requires-Dist: loguru (>=0.7.0)
Provides-Extra: dev
Requires-Dist: black ; extra == 'dev'
Requires-Dist: pytest ; extra == 'dev'
Requires-Dist: ruff ; extra == 'dev'
Provides-Extra: test
Requires-Dist: pytest ; extra == 'test'
